{
  "project_info": {
    "project_number": "123456789000",
    "firebase_url": "https://mockproject-1234.firebaseio.com",
    "project_id": "mockproject-1234",
    "storage_bucket": "mockproject-1234.appspot.com"
  },
  "client": [
    {
      "client_info": {
        "mobilesdk_app_id": "1:123456789000:android:f1bf012572b04063",
        "android_client_info": {
          "package_name": "com.clloret.days"
        }
      },
      "oauth_client": [
        {
          "client_id": "123456789000-c69gkdl3t66vfmpebsjhb6msoa8am5cq.apps.googleusercontent.com",
          "client_type": 3
        }
      ],
      "api_key": [
        {
          "current_key": "AIzbSzCn1N6LWIe6wthYyrgUUSAlUsdqMb-wvTo"
        }
      ],
      "services": {
        "appinvite_service": {
          "other_platform_oauth_client": [
            {
              "client_id": "123456789000-c69gkdl3t66vfmpebsjhb6msoa8am5cq.apps.googleusercontent.com",
              "client_type": 3
            }
          ]
        }
      }
    }
  ],
  "configuration_version": "1"
}